<!--Copyright TEI Consortium. 
Licensed under the GNU General Public License. 
See the file COPYING for details
$Date$
$Author$
-->
<elementSpec xmlns="http://www.tei-c.org/ns/1.0" module="textstructure" xml:id="BODY" usage="req" ident="body">
<equiv/>
<gloss>text body</gloss><gloss version="2006-10-28" xml:lang="ja">本文</gloss>
<desc>contains the whole body of a single unitary text, excluding any front or back matter.</desc><desc version="2006-10-28" xml:lang="ja"> 前付，後付を除いた作品の本文部分を示す．</desc><desc version="2006-10-15" xml:lang="es">contiene el cuerpo completo de un único texto unitario, excluyendo cualquier tipo de prólogo (front) o epílogo (back).</desc>
  <classes>
    <memberOf key="att.declaring"/>
  </classes>
  <content xmlns:rng="http://relaxng.org/ns/structure/1.0" xmlns="http://www.tei-c.org/ns/1.0">
    <rng:group>      <!-- this <group> exists just so odd2dtd can get parens in right place  -->
      <rng:zeroOrMore>
	<rng:choice>
	  <rng:ref name="model.divWrapper"/>
	  <rng:ref name="model.global"/>
	</rng:choice>
      </rng:zeroOrMore>
      <rng:choice>
        <rng:group>
          <rng:oneOrMore>
	    <rng:group>
	      <rng:ref name="macro.component"/>
	    </rng:group>
            <rng:zeroOrMore>
              <rng:ref name="model.global"/>
            </rng:zeroOrMore>
          </rng:oneOrMore>

          <rng:group>
            <rng:zeroOrMore>
              <rng:ref name="divGen"/>
              <rng:zeroOrMore>
                <rng:ref name="model.global"/>
              </rng:zeroOrMore>
            </rng:zeroOrMore>
            <rng:optional>
              <rng:choice>
                <rng:group>
                  <rng:ref name="div"/>
                  <rng:zeroOrMore>
                    <rng:choice>
                      <rng:ref name="div"/>
                      <rng:ref name="divGen"/>
                      <rng:ref name="model.global"/>
                    </rng:choice>
                  </rng:zeroOrMore>
                </rng:group>
                <rng:group>
                  <rng:ref name="div0"/>
                  <rng:zeroOrMore>
                    <rng:choice>
                      <rng:ref name="div0"/>
                      <rng:ref name="divGen"/>
                      <rng:ref name="model.global"/>
                    </rng:choice>
                  </rng:zeroOrMore>
                </rng:group>
                <rng:group>
                  <rng:ref name="div1"/>
                  <rng:zeroOrMore>
                    <rng:choice>
                      <rng:ref name="div1"/>
                      <rng:ref name="divGen"/>
                      <rng:ref name="model.global"/>
                    </rng:choice>
                  </rng:zeroOrMore>
                </rng:group>
              </rng:choice>
            </rng:optional>
          </rng:group>
        </rng:group>

        <rng:group>
          <rng:zeroOrMore>
            <rng:ref name="divGen"/>
            <rng:zeroOrMore>
              <rng:ref name="model.global"/>
            </rng:zeroOrMore>
          </rng:zeroOrMore>
          <rng:choice>
            <rng:group>
              <rng:ref name="div"/>
              <rng:zeroOrMore>
                <rng:choice>
                  <rng:ref name="div"/>
                  <rng:ref name="divGen"/>
                  <rng:ref name="model.global"/>
                </rng:choice>
              </rng:zeroOrMore>
            </rng:group>
            <rng:group>
              <rng:ref name="div0"/>
              <rng:zeroOrMore>
                <rng:choice>
                  <rng:ref name="div0"/>
                  <rng:ref name="divGen"/>
                  <rng:ref name="model.global"/>
                </rng:choice>
              </rng:zeroOrMore>
            </rng:group>
            <rng:group>
              <rng:ref name="div1"/>
              <rng:zeroOrMore>
                <rng:choice>
                  <rng:ref name="div1"/>
                  <rng:ref name="divGen"/>
                  <rng:ref name="model.global"/>
                </rng:choice>
              </rng:zeroOrMore>
            </rng:group>
          </rng:choice>
	</rng:group>
      </rng:choice>
      <rng:zeroOrMore>
	<rng:ref name="model.divWrapper.bottom"/>
      </rng:zeroOrMore>
    </rng:group>
  </content>
  <exemplum>
    <egXML xmlns="http://www.tei-c.org/ns/Examples"/>
  </exemplum>
  <remarks/>
  <listRef>
    <ptr target="#DS"/>
  </listRef>
</elementSpec>
