<?xml version="1.0" encoding="UTF-8"?><!--
Copyright TEI Consortium. 
Dual-licensed under CC-by and BSD2 licences 
See the file COPYING.txt for details
-->
<macroSpec xmlns="http://www.tei-c.org/ns/1.0" xmlns:rng="http://relaxng.org/ns/structure/1.0" module="tei" type="dt" ident="data.xmlName"><desc>defines attribute values which contain an XML name.</desc><content>
          <data xmlns="http://relaxng.org/ns/structure/1.0" type="NCName"/>
  </content><remarks>
    <p>The rules defining an XML name form a part of the XML Specification.</p>
  </remarks></macroSpec>