<?xml version="1.0" encoding="UTF-8"?>
<!--
Copyright TEI Consortium. 
Dual-licensed under CC-by and BSD2 licences 
See the file COPYING.txt for details
$Date$
$Id$
-->
<elementSpec xmlns="http://www.tei-c.org/ns/1.0" module="msdescription" ident="stamp">
  <equiv/>
  <gloss version="2007-06-12" xml:lang="fr">cachet</gloss>
  <desc>contains a word or phrase describing a
stamp or similar device.</desc>
  <desc version="2007-12-20" xml:lang="ko">스탬프 또는 유사한 도구를 기술하는 단어 또는 구를 포함한다.</desc>
  <desc version="2007-05-02" xml:lang="zh-TW">包含一個字詞，描述一個印記或是類似圖案。</desc>
  <desc version="2008-04-05" xml:lang="ja">
  印などにある語句を示す．
  </desc>
  <desc version="2009-04-17" xml:lang="fr">Contient un mot ou une expression décrivant un cachet ou
      une marque du même genre.</desc>
  <desc version="2007-11-06" xml:lang="it">contiene una parola o un sintagma che descrive un timbro o simile</desc>
  <desc version="2007-05-04" xml:lang="es">contiene una palabra o sintagma que describe un sello o una técnica similar.</desc>
  <classes>
    <memberOf key="att.global"/>
    <memberOf key="model.pPart.msdesc"/>
    <memberOf key="att.typed"/>
    <memberOf key="att.datable"/>
  </classes>
  <content>
    <ref xmlns="http://relaxng.org/ns/structure/1.0" name="macro.phraseSeq"/>
  </content>
  <exemplum xml:lang="mul">
    <egXML xmlns="http://www.tei-c.org/ns/Examples">
      <rubric>Apologyticu TTVLLIANI AC IGNORATIA IN XPO IHV<lb/>
SI NON LICET<lb/>
NOBIS RO<lb/>
manii imperii <stamp>Bodleian stamp</stamp>
            <lb/>
         </rubric>
    </egXML>
  </exemplum>
  <exemplum version="2008-04-06" xml:lang="fr">
    <egXML xmlns="http://www.tei-c.org/ns/Examples">
      <rubric>Apologyticu TTVLLIANI AC IGNORATIA IN XPO IHV<lb/> SI NON LICET<lb/> NOBIS RO<lb/>
          manii imperii <stamp>Bodleian stamp</stamp>
            <lb/>
         </rubric>
    </egXML>
  </exemplum>
  <exemplum xml:lang="zh-TW">
    <egXML xmlns="http://www.tei-c.org/ns/Examples">
      <rubric>乾隆御覽之寶<stamp>清乾隆玉璽</stamp>
            <lb/>
         </rubric>
    </egXML>
  </exemplum>
  <listRef>
    <ptr target="#mswat"/>
  </listRef>
</elementSpec>
