<?xml version="1.0" encoding="UTF-8"?>
<!--
Copyright TEI Consortium. 
Licensed under the GNU General Public License. 
See the file COPYING.txt for details
$Date$
$Id$
-->
<elementSpec xmlns="http://www.tei-c.org/ns/1.0" xmlns:rng="http://relaxng.org/ns/structure/1.0" ident="appInfo" module="header">
  <gloss>application information</gloss>
  <gloss version="2007-12-20" xml:lang="ko">애플리케이션 정보</gloss>
  <gloss version="2008-04-06" xml:lang="es">información de la aplicación</gloss>
  <gloss version="2008-03-30" xml:lang="fr">informations d'application</gloss>
  <gloss version="2007-11-06" xml:lang="it">informazioni su applicazione</gloss>
  <desc>records information about an application which has
  edited the TEI file. </desc>
  <desc version="2007-12-20" xml:lang="ko">TEI 파일을 편집한 애플리케이션에 관한 정보를 기록한다.</desc>
  <desc version="2008-04-06" xml:lang="es">recoge información sobre la aplicación que ha editado el fichero de TEI. </desc>
  <desc version="2008-04-05" xml:lang="ja">
  TEIファイルを編集したソフトウェアに関する情報を示す．
  </desc>
  <desc version="2008-12-09" xml:lang="fr">enregistre des informations sur l'application qui a
été utilisée pour traiter le fichier TEI.</desc>
  <desc version="2007-11-06" xml:lang="it">registra informazioni relative a un'applicazione che ha modificato il contenuto del file TEI</desc>
  <classes>
    <memberOf key="att.global"/>
    <memberOf key="model.encodingDescPart"/>
  </classes>
  <content>
    <rng:oneOrMore>
      <rng:ref name="model.applicationLike"/>
    </rng:oneOrMore>
  </content>
  <exemplum xml:lang="en">
    <egXML xmlns="http://www.tei-c.org/ns/Examples">
      <appInfo>
        <application version="1.24" ident="Xaira">
          <label>XAIRA Indexer</label>
          <ptr target="#P1"/>
        </application>
      </appInfo>
    </egXML>
  </exemplum>
</elementSpec>
