<?xml version="1.0" encoding="UTF-8"?>
<!-- © TEI Consortium. Dual-licensed under CC-by and BSD2 licenses; see the file COPYING.txt for details. -->
<?xml-model href="https://jenkins.tei-c.org/job/TEIP5-dev/lastSuccessfulBuild/artifact/P5/release/xml/tei/odd/p5.nvdl" type="application/xml" schematypens="http://purl.oclc.org/dsdl/nvdl/ns/structure/1.0"?>
<elementSpec xmlns="http://www.tei-c.org/ns/1.0" module="tagdocs" xml:id="gi-macroSpec" ident="macroSpec">
  <gloss versionDate="2007-07-04" xml:lang="en">macro specification</gloss>
  <gloss versionDate="2007-12-20" xml:lang="ko">매크로 명시</gloss>
  <gloss versionDate="2007-05-02" xml:lang="zh-TW"/>
  <gloss versionDate="2008-04-06" xml:lang="es">macroespecificación</gloss>
  <gloss versionDate="2007-06-12" xml:lang="fr">spécification de macro.</gloss>
  <gloss versionDate="2007-11-06" xml:lang="it">indicazione di macro</gloss>
  <desc versionDate="2005-01-14" xml:lang="en">documents the function and implementation of a pattern.</desc>
  <desc versionDate="2007-12-20" xml:lang="ko">유형의 기능 및 구현을 기록한다.</desc>
  <desc versionDate="2007-05-02" xml:lang="zh-TW">記錄模式的功能與實行。</desc>
  <desc versionDate="2008-04-05" xml:lang="ja">パタンの機能や実装を解説する。</desc>
  <desc versionDate="2007-06-12" xml:lang="fr">documente la fonction et l'implémentation d'un modèle.</desc>
  <desc versionDate="2007-05-04" xml:lang="es">documenta la función y la aplicación de un pattern (patrón).</desc>
  <desc versionDate="2007-01-21" xml:lang="it">documenta la funzione e l'applicazione di un pattern</desc>
  <classes>
    <memberOf key="att.global"/>
    <memberOf key="att.identified"/>
    <memberOf key="model.oddDecl"/>
  </classes>
  <content>
    <sequence>
      <alternate minOccurs="0" maxOccurs="unbounded">
        <classRef key="model.identSynonyms"/>
        <classRef key="model.descLike"/>
      </alternate>
      <alternate minOccurs="0" maxOccurs="1">
        <elementRef key="content"/>
        <elementRef key="valList"/>
      </alternate>
      <elementRef key="constraintSpec" minOccurs="0" maxOccurs="unbounded"/>
      <elementRef key="exemplum" minOccurs="0" maxOccurs="unbounded"/>
      <elementRef key="remarks" minOccurs="0" maxOccurs="unbounded"/>
      <elementRef key="listRef" minOccurs="0" maxOccurs="unbounded"/>
    </sequence>
  </content>
  <exemplum xml:lang="und">
    <egXML xmlns="http://www.tei-c.org/ns/Examples" xml:id="gi-macroSpec-egXML-hw" source="#UND">
      <macroSpec module="tei" ident="macro.phraseSeq">
        <content>
          <alternate minOccurs="0" maxOccurs="unbounded">
              <textNode/>
              <classRef key="model.gLike"/>
              <classRef key="model.phrase"/>
              <classRef key="model.global"/>
          </alternate>
        </content>
      </macroSpec>
    </egXML>
  </exemplum>
  <listRef>
    <ptr target="#TDcrystals"/>
    <ptr target="#TDENT"/>
  </listRef>
</elementSpec>
