<?xml version="1.0" encoding="UTF-8"?>
<!--
Copyright TEI Consortium. 
Dual-licensed under CC-by and BSD2 licences 
See the file COPYING.txt for details
$Date$
$Id$
-->
<elementSpec xmlns="http://www.tei-c.org/ns/1.0" module="dictionaries" ident="superEntry">
  <equiv/>
  <gloss versionDate="2007-06-12" xml:lang="fr">groupe d'entrées</gloss>
  <desc>groups a sequence of entries within any kind of lexical resource, such
  as a dictionary or lexicon which function as a single unit, for
  example a set of homographs.</desc>
  <desc versionDate="2007-12-20" xml:lang="ko">동형이의어 집합의 연속된 표제 항목을 모아 놓는다.</desc>
  <desc versionDate="2007-05-02" xml:lang="zh-TW">匯集一組同形異義字的連續辭條。</desc>
  <desc versionDate="2008-04-05" xml:lang="ja">
  同形異義語の集合にある，一連の項目をまとめる．
  </desc>
  <desc versionDate="2007-06-12" xml:lang="fr">regroupe des entrées successives pour un ensemble
			d'homographes.</desc>
  <desc versionDate="2007-05-04" xml:lang="es">agrupa las entradas sucesivas para una serie de homógrafos.</desc>
  <desc versionDate="2007-01-21" xml:lang="it">raggruppa voci successive per una serie di omografi.</desc>
  <classes>
    <memberOf key="att.global"/>
    <memberOf key="model.entryLike"/>
    <memberOf key="att.entryLike"/>
    <memberOf key="model.entryPart"/>
    <memberOf key="att.sortable"/>
  </classes>
  <content>
    <choice xmlns="http://relaxng.org/ns/structure/1.0">
      <group>
        <optional>
          <ref name="form"/>
        </optional>
        <oneOrMore>
          <ref name="entry"/>
        </oneOrMore>
      </group>
      <ref name="dictScrap"/>
    </choice>
  </content>
  <exemplum xml:lang="en">
    <egXML xmlns="http://www.tei-c.org/ns/Examples">
      <superEntry>
        <form>
          <orth>abandon</orth>
          <hyph>a|ban|don</hyph>
          <pron>@"band@n</pron>
        </form>
        <entry n="1">
          <gramGrp>
            <pos>v</pos>
            <subc>T1</subc>
          </gramGrp>
          <sense n="1">
            <def>to leave completely and for ever ... </def>
          </sense>
          <sense n="2"/>
        </entry>
        <entry n="2">
          <gramGrp>
            <pos>n</pos>
            <subc>U</subc>
          </gramGrp>
          <def>the state when one's feelings and actions are uncontrolled; freedom from
                        control</def>
        </entry>
      </superEntry>
    </egXML>
  </exemplum>
  <exemplum versionDate="2008-04-06" xml:lang="fr">
    <egXML xmlns="http://www.tei-c.org/ns/Examples" source="#fr-ex-Grand-Robert">
      <superEntry>
        <form>
          <orth>homme</orth>
          <hyph>hom|me</hyph>
          <pron>óm</pron>
        </form>
        <entry n="1">
          <gramGrp>
            <pos>n.</pos>
          </gramGrp>
          <sense n="1">
            <def>Etre appartenant à l'espèce animale la plus évoluée de la Terre</def>
          </sense>
          <sense n="2"/>
        </entry>
        <entry n="2">
          <gramGrp>
            <pos>n.</pos>
          </gramGrp>
          <def>Etre humain mâle et (le plus souvent) adulte.</def>
        </entry>
      </superEntry>
    </egXML>
  </exemplum>
  <exemplum xml:lang="zh-TW">
    <egXML xmlns="http://www.tei-c.org/ns/Examples">
      <superEntry>
        <form>
          <orth>弼</orth>
          <hyph> (因漢字無法以連字符號拆解，故不提供範例。)</hyph>
          <pron>bi4</pron>
        </form>
        <entry n="1">
          <gramGrp>
            <pos>動詞</pos>
            <subc>及物</subc>
          </gramGrp>
          <sense n="1">
            <def>輔助；矯正過失</def>
          </sense>
          <sense n="2"/>
        </entry>
        <entry n="2">
          <gramGrp>
            <pos>名詞</pos>
            <subc>可數</subc>
          </gramGrp>
          <def>古時矯正弓的器具</def>
        </entry>
      </superEntry>
    </egXML>
  </exemplum>
  <listRef>
    <ptr target="#DIBO"/>
  </listRef>
</elementSpec>
