<?xml version="1.0" encoding="utf-8"?>
<!--Copyright TEI Consortium. 
Licensed under the GNU General Public License. 
See the file COPYING for details
$Date$

$Id$
-->
<elementSpec xmlns="http://www.tei-c.org/ns/1.0" module="header" xml:id="TAGUSAGE" usage="rec" ident="tagUsage">
  <equiv/>
  <gloss version="2007-05-04" xml:lang="es">uso de etiqueta</gloss>
  <gloss version="2007-08-25" xml:lang="it">tagUsage</gloss>
  <gloss version="2007-01-21" xml:lang="it">Utilizzo dei marcatori</gloss>
  <gloss version="2006-10-28" xml:lang="ja">タグの使用法</gloss>
  <gloss xml:lang="zh-tw">標籤使用</gloss>
  <gloss xml:lang="fr">utilisation de la balise</gloss>
  <desc>supplies information about the usage of a specific element
within a text. </desc>
  <desc version="2007-01-21" xml:lang="it">fornisce informazioni circa l'uso di uno specifico elemento all'interno di un testo.</desc>
  <desc version="2007-05-04" xml:lang="es">proporciona información sobre el uso de un elemento específico al interno del texto.</desc>
  <desc version="2006-10-28" xml:lang="ja"> 特定タグの使用方法を示す．</desc>
  <desc xml:lang="zh-tw">提供符合TEI標準的文件最外層的&lt;文件&gt;(&lt;text&gt;)當中某個特定元素的使用資訊。</desc>
  <desc xml:lang="fr">L’élément Usage de la balise <gi>&gt;tagUsage</gi> fournit des informations sur l’utilisation d’un élément spécifique dans le texte.</desc>
  <content>
    <rng:ref xmlns:rng="http://relaxng.org/ns/structure/1.0" name="macro.limitedContent"/>
  </content>
  <attList>
    <attDef ident="gi" usage="req">
      <gloss>element name</gloss>
      <desc>the name (generic identifier) of the element indicated by
      the tag.</desc>
      <desc version="2007-01-21" xml:lang="it">il nome (identificatore generico) dell'elemento indicato dal marcatore.</desc>
      <desc version="2007-05-04" xml:lang="es">el nombre (identificador genérico) de un elemento indicado mediante una etiqueta.</desc>
      <desc version="2006-10-28" xml:lang="ja">タグの名前(共通識別子)．</desc>
      <desc xml:lang="fr">nom (identifiant générique) de l’élément
      indiqué dans la balise.</desc>
      <datatype>
        <rng:ref xmlns:rng="http://relaxng.org/ns/structure/1.0" name="data.name"/>
      </datatype>
      <valDesc>the name of an element within the namespace indicated
      by the parent <gi>namespace</gi> element</valDesc>
    </attDef>
    <attDef ident="occurs" usage="rec">
      <equiv/>
      <desc>specifies the number of occurrences of this element within the text.</desc>
      <desc version="2007-01-21" xml:lang="it">specifica il numero di occorrenze dell'elemento nel testo.</desc>
      <desc version="2007-05-04" xml:lang="es">especifica el número de veces que un elemento determinado aparece en el texto.</desc>
      <desc version="2006-10-28" xml:lang="ja">テキスト中における当該タグの出現番号．</desc>
      <desc xml:lang="fr">spécifie le nombre d’occurrences de cet élément dans le texte.</desc>
      <datatype>
        <rng:ref xmlns:rng="http://relaxng.org/ns/structure/1.0" name="data.count"/>
      </datatype>
      <valDesc>an integer number greater than zero</valDesc>
    </attDef>
    <attDef ident="withId" usage="rec">
      <gloss>with unique identifier</gloss>
      <desc>specifies the number of occurrences of this element within
      the text which bear a distinct value for the global
      <att>xml:id</att> attribute. </desc>
      <desc version="2007-01-21" xml:lang="it">specifica il numero di occorrenze dell'elemento nel testo e che reca un valore distinto dall'attributo globale <att>xml:id</att>.</desc>
      <desc version="2007-05-04" xml:lang="es">indica el número de veces que este elemento aparece en el texto con un valor distintivo apara el atributo global <att>xml:id</att>. </desc>
      <desc version="2006-10-28" xml:lang="ja">属性xml:idを持つテキスト中における当該タグの出現番号．</desc>
      <desc xml:lang="fr">spécifie le nombre d’occurrences de cet
      élément dans le texte qui porte une valeur donnée pour
      l’attribut global <att>xml:id</att>.</desc>
      <datatype>
        <rng:ref xmlns:rng="http://relaxng.org/ns/structure/1.0" name="data.count"/>
      </datatype>
      <valDesc>an integer number greater than zero</valDesc>
    </attDef>
    <attDef ident="render" usage="opt">
      <equiv/>
      <desc>specifies the identifier of a <gi>rendition</gi> element
      which defines how this element is to be rendered.</desc>
      <desc version="2007-01-21" xml:lang="it">indica l'identificatore di un elemento <gi>rendition</gi> che definisce in che modo è stato reso l'elemento</desc>
      <desc version="2007-05-04" xml:lang="es">especifica el identificador de un elemento <gi>rendition</gi> que define cómo este elemento ha de ser interpretado.</desc>
      <desc version="2006-10-28" xml:lang="ja">当該要素がどのように表現されるかを規定する要素のIDを示す．</desc>
      <desc xml:lang="fr">spécifie l’identifiant d’un élément de
      restitution <gi>rendition</gi> qui définit comment cet élément
      doit être restitué.</desc>
      <datatype>
        <rng:ref xmlns:rng="http://relaxng.org/ns/structure/1.0" name="data.pointer"/>
      </datatype>
      <valDesc>an identifier specified as the value of the
      <att>xml:id</att> attribute on some <gi>rendition</gi> element
      in the current document.</valDesc>
    </attDef>
  </attList>
  <exemplum>
    <egXML xmlns="http://www.tei-c.org/ns/Examples">
      <tagsDecl>
        <rendition xml:id="it">Render using a slant or italic variant
	on the current font</rendition>
<!-- ... -->
        <namespace name="http://www.tei-c.org/ns/1.0">
          <tagUsage gi="hi" occurs="28" withId="2" render="#it">
	  Used to mark English words italicised in the copy text.</tagUsage>
          <tagUsage gi="foreign" render="#it">Used to mark non-English
	  words in the copy text.</tagUsage>
<!-- ... -->
        </namespace>
      </tagsDecl>
    </egXML>
  </exemplum>
  <exemplum xml:lang="fr">
    <egXML xmlns="http://www.tei-c.org/ns/Examples">
      <tagUsage gi="hi" occurs="28" withId="2" render="#it"> Utilisé
      seulement pour marquer les mots anglais en italiques dans le
      texte de la copie.</tagUsage>
    </egXML>
  </exemplum>
  <listRef>
    <ptr target="#HD57"/>
  </listRef>
</elementSpec>
