<?xml version="1.0" encoding="utf-8"?>
<!--Copyright TEI Consortium. 
Licensed under the GNU General Public License. 
See the file COPYING for details
$Date$

$Id$
-->
<elementSpec xmlns="http://www.tei-c.org/ns/1.0" module="header" xml:id="TEXTCLAS" usage="opt" ident="textClass">
  <equiv/>
  <gloss>text classification</gloss>
  <gloss version="2007-01-21" xml:lang="it">classificazione del testo</gloss>
  <gloss version="2007-05-04" xml:lang="es">clasificación de texto</gloss>
  <gloss version="2006-10-28" xml:lang="ja">テキストの分類</gloss>
  <gloss xml:lang="zh-tw">文件分類</gloss>
  <gloss xml:lang="fr">Classification du texte</gloss>
  <desc>groups information which describes the nature or topic of a text
in terms of a standard classification scheme, thesaurus, etc.</desc>
  <desc version="2007-01-21" xml:lang="it">raggruppa le informazioni che descrivono la natura o l'argomento di un testo secondo uno schema di classificazione standard, un dizionario i sinonimi, ecc.</desc>
  <desc version="2007-05-04" xml:lang="es">agrupa información que describe la naturaleza o la temática de un texto en términos de un esquema de clasificación estándard. </desc>
  <desc version="2006-10-28" xml:lang="ja"> 当該テキストの性質やトピックに関する情報をまとめる．</desc>
  <desc xml:lang="zh-tw">匯集以標準分類架構、索引典等來描述文件性質或主題的資訊。</desc>
  <desc xml:lang="fr">L’élément Classification du texte <gi>textClass</gi> regroupe des informations décrivant la nature ou le sujet d’un texte selon des termes issus d’un système de classification standardisé, d’un thésaurus, etc.</desc>
  <classes>
    <memberOf key="model.profileDescPart"/>
    <memberOf key="att.declarable"/>
  </classes>
  <content>
    <rng:zeroOrMore xmlns:rng="http://relaxng.org/ns/structure/1.0">
      <rng:choice>
        <rng:ref name="classCode"/>
        <rng:ref name="catRef"/>
        <rng:ref name="keywords"/>
      </rng:choice>
    </rng:zeroOrMore>
  </content>
  <exemplum>
    <egXML xmlns="http://www.tei-c.org/ns/Examples">
      <taxonomy>
        <category xml:id="acprose">
          <catDesc>Academic prose</catDesc>
        </category>
<!-- other categories here -->
      </taxonomy>
<!-- ... -->
      <textClass>
        <catRef target="#acprose"/>
        <classCode scheme="http://www.udcc.org">001.9</classCode>
        <keywords scheme="http://authorities.loc.gov">
          <list>
            <item>End of the world</item>
            <item>History - philosophy</item>
          </list>
        </keywords>
      </textClass>
    </egXML>
  </exemplum>
  <exemplum xml:lang="fr">
    <egXML xmlns="http://www.tei-c.org/ns/Examples">
      <textClass>
        <catRef target="#acprose"/>
        <classCode scheme="http://www.udcc.org">001.9</classCode>
        <keywords scheme="http://authorities.loc.gov/">
          <list>
            <item>Fin du monde</item>
            <item>Histoire - philosophie</item>
          </list>
        </keywords>
      </textClass>
    </egXML>
  </exemplum>
  <listRef>
    <ptr target="#HD43"/>
  </listRef>
</elementSpec>
