<?xml version="1.0" encoding="utf-8"?>
<!--
Copyright TEI Consortium. 
Licensed under the GNU General Public License. 
See the file COPYING.txt for details
$Date$
$Id$
-->
<classSpec xmlns="http://www.tei-c.org/ns/1.0" type="model" module="tei" ident="model.persEventLike">


  <desc version="2008-01-31" xml:lang="ja" >
  個人史中にある特定の事象を示す要素をまとめる．例えば，出生，婚姻，任
  命など．
  </desc>

  <classes>
    <memberOf key="model.personPart"/>
  </classes>

  <remarks version="2008-01-31" xml:lang="ja" >
    <p>
    個人が持つ特徴ではなく，個人が獲得する特徴で，新しい状態に移行する
    もの．
    </p>
  </remarks>

</classSpec>
